ckanext_logstash-0.0.2-py3.7-nspkg.pth
ckanext/logstash/__init__.py
ckanext/logstash/plugins.py
ckanext/sentry/__init__.py
ckanext/sentry/plugins.py
ckanext_logstash-0.0.2.dist-info/METADATA
ckanext_logstash-0.0.2.dist-info/WHEEL
ckanext_logstash-0.0.2.dist-info/entry_points.txt
ckanext_logstash-0.0.2.dist-info/namespace_packages.txt
ckanext_logstash-0.0.2.dist-info/top_level.txt
ckanext_logstash-0.0.2.dist-info/RECORD
