Metadata-Version: 2.1
Name: ckanext-logstash
Version: 0.0.2
Summary: Logstash support for CKAN
Home-page: https://github.com/datopian/ckanext-logstash
Author: Adam Kariv
Author-email: adam.kariv@datopian.org
License: UNKNOWN
Keywords: CKAN,Logstash
Platform: UNKNOWN
Classifier: Development Status :: 3 - Alpha
Classifier: Environment :: Web Environment
Classifier: Framework :: Pylons
Classifier: Intended Audience :: Developers
Classifier: Programming Language :: Python :: 2
Classifier: Programming Language :: Python :: 2.7
Classifier: Programming Language :: Python
Classifier: Topic :: Internet :: WWW/HTTP :: Session
Classifier: Topic :: Internet :: WWW/HTTP :: WSGI :: Middleware
Classifier: Topic :: Software Development :: Libraries :: Python Modules
Classifier: Topic :: System :: Systems Administration :: Authentication/Directory
Requires-Dist: python-logstash
